adaptivecards/__init__.py
adaptivecards/adaptivecard.py
adaptivecards/baseobject.py
adaptivecards/containers.py
adaptivecards/elements.py
adaptivecards-0.4.1.dist-info/LICENSE
adaptivecards-0.4.1.dist-info/METADATA
adaptivecards-0.4.1.dist-info/WHEEL
adaptivecards-0.4.1.dist-info/top_level.txt
adaptivecards-0.4.1.dist-info/RECORD
