Metadata-Version: 2.1
Name: adaptivecards
Version: 0.4.1
Summary: Author adaptive cards in pure python
Home-page: https://github.com/huuhoa/adaptivecards
Author: Huu Hoa NGUYEN
Author-email: huuhoa@gmail.com
License: MIT License
Keywords: adaptivecards
Platform: UNKNOWN
Classifier: Development Status :: 2 - Pre-Alpha
Classifier: Intended Audience :: Developers
Classifier: Natural Language :: English
Classifier: Programming Language :: Python :: 3
Classifier: Programming Language :: Python :: 3.7
Classifier: Programming Language :: Python :: 3.8
Classifier: Programming Language :: Python :: 3.9
Classifier: Programming Language :: Python :: 3.10
